LICENSE
ipycopilot/__init__.py
ipycopilot/__main__.py
ipycopilot/app.py
ipycopilot/static/index.html
ipycopilot/static/vendor/particles.min.js
ipycopilot-0.1.1.dist-info/licenses/LICENSE
ipycopilot-0.1.1.dist-info/METADATA
ipycopilot-0.1.1.dist-info/WHEEL
ipycopilot-0.1.1.dist-info/entry_points.txt
ipycopilot-0.1.1.dist-info/top_level.txt
ipycopilot-0.1.1.dist-info/RECORD
