Metadata-Version: 2.4
Name: ipycopilot
Version: 0.1.1
Summary: Desktop landing page for ipycopilot – PyWebview + React with particles.js
Author-email: Your Name <you@example.com>
License: ipycopilot COMMUNITY & COMMERCIAL LICENSE (NO-MODIFICATION)
Classifier: License :: Other/Proprietary License
Classifier: Programming Language :: Python :: 3
Classifier: Programming Language :: Python :: 3 :: Only
Classifier: Operating System :: OS Independent
Requires-Python: >=3.8
License-File: LICENSE
Requires-Dist: pywebview<5,>=4
Requires-Dist: pywebview[qt]
Requires-Dist: qtpy
Provides-Extra: gtk
Requires-Dist: pywebview[gtk]; extra == "gtk"
Dynamic: license-file
